pyproject_api/__init__.py
pyproject_api/__main__.py
pyproject_api/_backend.py
pyproject_api/_backend.pyi
pyproject_api/_frontend.py
pyproject_api/_util.py
pyproject_api/_version.py
pyproject_api/_via_fresh_subprocess.py
pyproject_api/py.typed
pyproject_api-1.7.2.dist-info/METADATA
pyproject_api-1.7.2.dist-info/WHEEL
pyproject_api-1.7.2.dist-info/licenses/LICENSE
pyproject_api-1.7.2.dist-info/RECORD
