Metadata-Version: 2.3
Name: pyproject-api
Version: 1.7.2
Summary: API to interact with the python pyproject.toml based projects
Project-URL: Changelog, https://github.com/tox-dev/pyproject-api/releases
Project-URL: Homepage, https://pyproject-api.readthedocs.io
Project-URL: Source, https://github.com/tox-dev/pyproject-api
Project-URL: Tracker, https://github.com/tox-dev/pyproject-api/issues
Author-email: Bernát Gábor <gaborjbernat@gmail.com>
Maintainer-email: Bernát Gábor <gaborjbernat@gmail.com>
License-Expression: MIT
License-File: LICENSE
Keywords: environments,isolated,testing,virtual
Classifier: Development Status :: 5 - Production/Stable
Classifier: Framework :: tox
Classifier: Intended Audience :: Developers
Classifier: License :: OSI Approved :: MIT License
Classifier: Operating System :: MacOS :: MacOS X
Classifier: Operating System :: Microsoft :: Windows
Classifier: Operating System :: POSIX
Classifier: Programming Language :: Python :: 3 :: Only
Classifier: Programming Language :: Python :: 3.8
Classifier: Programming Language :: Python :: 3.9
Classifier: Programming Language :: Python :: 3.10
Classifier: Programming Language :: Python :: 3.11
Classifier: Programming Language :: Python :: 3.12
Classifier: Programming Language :: Python :: 3.13
Classifier: Topic :: Software Development :: Libraries
Classifier: Topic :: Software Development :: Testing
Classifier: Topic :: Utilities
Requires-Python: >=3.8
Requires-Dist: packaging>=24.1
Requires-Dist: tomli>=2.0.1; python_version < '3.11'
Provides-Extra: docs
Requires-Dist: furo>=2024.8.6; extra == 'docs'
Requires-Dist: sphinx-autodoc-typehints>=2.4.1; extra == 'docs'
Provides-Extra: testing
Requires-Dist: covdefaults>=2.3; extra == 'testing'
Requires-Dist: pytest-cov>=5; extra == 'testing'
Requires-Dist: pytest-mock>=3.14; extra == 'testing'
Requires-Dist: pytest>=8.3.3; extra == 'testing'
Requires-Dist: setuptools>=75.1; extra == 'testing'
